build/lib/build/lib/build/lib/build/lib/build/lib/build/lib/simple_proxy/__init__.py
build/lib/build/lib/build/lib/build/lib/build/lib/build/lib/simple_proxy/__main__.py
build/lib/build/lib/build/lib/build/lib/build/lib/build/lib/simple_proxy/clients.py
build/lib/build/lib/build/lib/build/lib/build/lib/build/lib/simple_proxy/run.py
build/lib/build/lib/build/lib/build/lib/build/lib/build/lib/simple_proxy/version.py
build/lib/build/lib/build/lib/build/lib/build/lib/build/lib/simple_proxy/handler/__init__.py
build/lib/build/lib/build/lib/build/lib/build/lib/build/lib/simple_proxy/handler/echo_channel_handler.py
build/lib/build/lib/build/lib/build/lib/build/lib/build/lib/simple_proxy/handler/http_proxy_channel_handler.py
build/lib/build/lib/build/lib/build/lib/build/lib/build/lib/simple_proxy/handler/proxy_channel_handler.py
build/lib/build/lib/build/lib/build/lib/build/lib/build/lib/simple_proxy/handler/shell_channel_handler.py
build/lib/build/lib/build/lib/build/lib/build/lib/build/lib/simple_proxy/handler/socks5_proxy_channel_handler.py
build/lib/build/lib/build/lib/build/lib/build/lib/build/lib/simple_proxy/utils/__init__.py
build/lib/build/lib/build/lib/build/lib/build/lib/build/lib/simple_proxy/utils/certutils.py
build/lib/build/lib/build/lib/build/lib/build/lib/build/lib/simple_proxy/utils/logutils.py
build/lib/build/lib/build/lib/build/lib/build/lib/build/lib/simple_proxy/utils/netutils.py
build/lib/build/lib/build/lib/build/lib/build/lib/build/lib/simple_proxy/utils/osutils.py
build/lib/build/lib/build/lib/build/lib/build/lib/build/lib/simple_proxy/utils/proxyutils.py
build/lib/build/lib/build/lib/build/lib/build/lib/build/lib/simple_proxy/utils/stringutils.py
build/lib/build/lib/build/lib/build/lib/build/lib/build/lib/simple_proxy/utils/tlsutils.py
build/lib/build/lib/build/lib/build/lib/build/lib/simple_proxy/__init__.py
build/lib/build/lib/build/lib/build/lib/build/lib/simple_proxy/__main__.py
simple_proxy-0.0.30.dist-info/licenses/LICENSE
simple_proxy-0.0.30.dist-info/METADATA
simple_proxy-0.0.30.dist-info/WHEEL
simple_proxy-0.0.30.dist-info/entry_points.txt
simple_proxy-0.0.30.dist-info/top_level.txt
simple_proxy-0.0.30.dist-info/RECORD
