Metadata-Version: 2.4
Name: simple_proxy
Version: 0.0.30
Summary: A simple NIO proxy tool
Home-page: https://github.com/ruanhao/simple-proxy
Author-email: Hao Ruan <ruanhao1116@gmail.com>
License: MIT
Project-URL: Homepage, https://github.com/ruanhao/simple-proxy
Keywords: network,tcp,non-blocking,proxy
Classifier: Intended Audience :: Developers
Classifier: License :: OSI Approved :: MIT License
Classifier: Natural Language :: English
Classifier: Operating System :: OS Independent
Classifier: Programming Language :: Python
Classifier: Programming Language :: Python :: 3
Classifier: Programming Language :: Python :: 3.7
Classifier: Programming Language :: Python :: 3.8
Classifier: Programming Language :: Python :: 3.9
Classifier: Programming Language :: Python :: 3.10
Classifier: Programming Language :: Python :: 3.11
Classifier: Programming Language :: Python :: 3.12
Classifier: Programming Language :: Python :: 3.13
Classifier: Programming Language :: Python :: 3 :: Only
Classifier: Topic :: Software Development :: Libraries
Requires-Python: <4,>=3.7
License-File: LICENSE
Requires-Dist: click-option-group
Requires-Dist: py-netty>=1.0.8
Requires-Dist: cryptography>=42.0.0
Requires-Dist: attrs>=22.1.0
Provides-Extra: dev
Requires-Dist: pip-chill; extra == "dev"
Provides-Extra: test
Requires-Dist: pytest>=7.4.0; extra == "test"
Requires-Dist: pytest-cov>=4.1.0; extra == "test"
Requires-Dist: pytest-asyncio>=0.21.0; extra == "test"
Requires-Dist: pytest-mock>=3.11.1; extra == "test"
Requires-Dist: coverage[toml]>=7.3.0; extra == "test"
Dynamic: license-file
